common/__init__.py
common/descriptors.py
common/variables.py
database/__init__.py
database/server_database.py
deсorators/__init__.py
deсorators/call_logger.py
deсorators/login_required.py
gui/__init__.py
gui/add_user.py
gui/remove_user.py
gui/server_gui.py
loggers/__init__.py
loggers/server_logs.py
messagers/__init__.py
messagers/abstract_messenger.py
messagers/server_messenger.py
meta_classes/__init__.py
meta_classes/server_maker.py
async_message_server-0.0.1.dist-info/METADATA
async_message_server-0.0.1.dist-info/WHEEL
async_message_server-0.0.1.dist-info/top_level.txt
async_message_server-0.0.1.dist-info/RECORD
