Metadata-Version: 2.1
Name: async-message-server
Version: 0.0.1
Summary: study gb async-message-server
Home-page: https://github.com/LuckyBustard/async_chat_gb
Author: Mytsykov Sergey
Author-email: smytsykov@gmail.com
Requires-Dist: PyQt6
Requires-Dist: sqlalchemy
